moeximporter/MoexCandlePeriods.py
moeximporter/MoexImporter.py
moeximporter/MoexRequests.py
moeximporter/MoexSecurity.py
moeximporter/MoexSessions.py
moeximporter/_MoexRequests.py
moeximporter/__init__.py
moeximporter-0.2.4.dist-info/LICENSE.txt
moeximporter-0.2.4.dist-info/METADATA
moeximporter-0.2.4.dist-info/WHEEL
moeximporter-0.2.4.dist-info/top_level.txt
moeximporter-0.2.4.dist-info/RECORD
